sameh_stirling/__init__.py
sameh_stirling/bubble_chart.py
sameh_stirling/stacked_bar.py
tests/__init__.py
tests/test_bubble_chart.py
tests/test_stacked_bar.py
sameh_stirling-0.0.6.dist-info/METADATA
sameh_stirling-0.0.6.dist-info/WHEEL
sameh_stirling-0.0.6.dist-info/top_level.txt
sameh_stirling-0.0.6.dist-info/RECORD
