Metadata-Version: 2.1
Name: sameh-stirling
Version: 0.0.6
Summary: A library for creating Dash interactive charts
Home-page: https://github.com/samehsalah/sameh-stirling
Author: Sameh Salah
Author-email: Sameh Salah <samehsalah83@gmail.com>
Project-URL: Homepage, https://github.com/samehsalah/sameh-stirling
Classifier: Programming Language :: Python :: 3
Classifier: License :: OSI Approved :: MIT License
Classifier: Operating System :: OS Independent
Requires-Python: >=3.6
Requires-Dist: dash
Requires-Dist: dash-bootstrap-components
Requires-Dist: pandas
Requires-Dist: plotly
Requires-Dist: matplotlib
